so4gp/__configs__.py
so4gp/__init__.py
so4gp/data_gp.py
so4gp/gradual_patterns.py
so4gp/utils.py
so4gp/algorithms/__init__.py
so4gp/algorithms/cluster_gp.py
so4gp/algorithms/graank.py
so4gp/algorithms/graank_aco.py
so4gp/algorithms/graank_ga.py
so4gp/algorithms/graank_hc.py
so4gp/algorithms/graank_pso.py
so4gp/algorithms/graank_rand.py
so4gp/algorithms/grad_pfs.py
so4gp/algorithms/numeric_ss.py
so4gp/algorithms/tgrad.py
so4gp/algorithms/tgrad_ami.py
so4gp-0.7.1.dist-info/licenses/LICENSE
so4gp-0.7.1.dist-info/METADATA
so4gp-0.7.1.dist-info/WHEEL
so4gp-0.7.1.dist-info/top_level.txt
so4gp-0.7.1.dist-info/RECORD
