Metadata-Version: 2.4
Name: so4gp
Version: 0.7.1
Summary: Some Python optimization algorithms for mining gradual patterns.
Author-email: Dickson Owuor <owuordickson@gmail.com>, Anne Laurent <laurent@lirmm.fr>
Maintainer-email: Dickson Owuor <owuordickson@gmail.com>
License:                     GNU GENERAL PUBLIC LICENSE
Project-URL: Homepage, https://github.com/owuordickson/sogp_pypi
Project-URL: Documentation, http://sogp-pypi.readthedocs.io
Project-URL: Repository, https://github.com/owuordickson/sogp_pypi.git
Project-URL: Bug Tracker, https://github.com/owuordickson/sogp_pypi/issues
Project-URL: Changelog, https://github.com/owuordickson/sogp_pypi/blob/main/CHANGELOG.md
Keywords: gradual patterns,GRAANK,ant-colony-optimization,data-mining,swarm-intelligence
Classifier: Development Status :: 4 - Beta
Classifier: Programming Language :: Python :: 3.12
Classifier: License :: OSI Approved :: MIT License
Classifier: Operating System :: OS Independent
Classifier: Intended Audience :: Science/Research
Classifier: Topic :: Scientific/Engineering :: Artificial Intelligence
Requires-Python: >=3.12
License-File: LICENSE
Requires-Dist: numpy~=2.3.2
Requires-Dist: pandas~=2.3.1
Requires-Dist: scikit-fuzzy~=0.5.0
Requires-Dist: scikit-learn~=1.7.1
Requires-Dist: python-dateutil~=2.9.0.post0
Requires-Dist: tabulate~=0.9.0
Requires-Dist: seaborn~=0.13.2
Requires-Dist: matplotlib~=3.10.5
Dynamic: license-file
